opendatalab/__init__.py
opendatalab/__version__.py
opendatalab/exception.py
opendatalab/py.typed
opendatalab/utils.py
opendatalab/cli/__init__.py
opendatalab/cli/cmd.py
opendatalab/cli/config.py
opendatalab/cli/custom.py
opendatalab/cli/get.py
opendatalab/cli/info.py
opendatalab/cli/login.py
opendatalab/cli/logout.py
opendatalab/cli/ls.py
opendatalab/cli/policy.py
opendatalab/cli/search.py
opendatalab/cli/upgrade.py
opendatalab/cli/utility.py
opendatalab/client/__init__.py
opendatalab/client/api.py
opendatalab/client/client.py
opendatalab/client/uaa.py
opendatalab/dataset/__init__.py
opendatalab/dataset/dataset.py
opendl-0.0.3b2.dist-info/LICENSE
opendl-0.0.3b2.dist-info/METADATA
opendl-0.0.3b2.dist-info/WHEEL
opendl-0.0.3b2.dist-info/entry_points.txt
opendl-0.0.3b2.dist-info/top_level.txt
opendl-0.0.3b2.dist-info/RECORD
